odoo/addons/purchase_request_analytic/README.rst
odoo/addons/purchase_request_analytic/__init__.py
odoo/addons/purchase_request_analytic/__manifest__.py
odoo/addons/purchase_request_analytic/i18n/purchase_request_analytic.pot
odoo/addons/purchase_request_analytic/models/__init__.py
odoo/addons/purchase_request_analytic/models/purchase_request.py
odoo/addons/purchase_request_analytic/readme/CONTRIBUTORS.rst
odoo/addons/purchase_request_analytic/readme/DESCRIPTION.rst
odoo/addons/purchase_request_analytic/readme/HISTORY.rst
odoo/addons/purchase_request_analytic/readme/USAGE.rst
odoo/addons/purchase_request_analytic/static/description/icon.png
odoo/addons/purchase_request_analytic/static/description/index.html
odoo/addons/purchase_request_analytic/tests/__init__.py
odoo/addons/purchase_request_analytic/tests/test_purchase_request_analytic.py
odoo/addons/purchase_request_analytic/views/purchase_request_views.xml
odoo13_addon_purchase_request_analytic-13.0.1.0.1.dev3.dist-info/METADATA
odoo13_addon_purchase_request_analytic-13.0.1.0.1.dev3.dist-info/WHEEL
odoo13_addon_purchase_request_analytic-13.0.1.0.1.dev3.dist-info/top_level.txt
odoo13_addon_purchase_request_analytic-13.0.1.0.1.dev3.dist-info/RECORD
